sonofabatch/__init__.py
sonofabatch/babel.py
sonofabatch/job.py
sonofabatch/master.py
sonofabatch/node.py
sonofabatch/populate.py
sonofabatch/queue.py
sonofabatch-0.0.2.dist-info/LICENSE.md
sonofabatch-0.0.2.dist-info/METADATA
sonofabatch-0.0.2.dist-info/WHEEL
sonofabatch-0.0.2.dist-info/top_level.txt
sonofabatch-0.0.2.dist-info/RECORD
