Metadata-Version: 2.1
Name: sonofabatch
Version: 0.0.2
Summary: A very simple and really fast batch processing toolkit.
Home-page: https://bitbucket.org/mikeortman/sonofabatch
Author: Mike Ortman
Author-email: mikeortman@gmail.com
License: UNKNOWN
Platform: UNKNOWN
Requires-Python: >=3
